noneprompt/__init__.py
noneprompt/__main__.py
noneprompt/cli/__init__.py
noneprompt/cli/_options.py
noneprompt/cli/checkbox.py
noneprompt/cli/confirm.py
noneprompt/cli/input.py
noneprompt/cli/list.py
noneprompt/prompts/__init__.py
noneprompt/prompts/_base.py
noneprompt/prompts/_choice.py
noneprompt/prompts/checkbox.py
noneprompt/prompts/confirm.py
noneprompt/prompts/input.py
noneprompt/prompts/list.py
noneprompt/py.typed
noneprompt/utils.py
noneprompt-0.1.10.dist-info/WHEEL
noneprompt-0.1.10.dist-info/entry_points.txt
noneprompt-0.1.10.dist-info/METADATA
noneprompt-0.1.10.dist-info/RECORD
