Metadata-Version: 2.4
Name: noneprompt
Version: 0.1.10
Summary: Prompt toolkit for console interaction
Keywords: prompt,inquirer,prompt-toolkit
Author: yanyongyu
Author-email: yanyongyu <yyy@nonebot.dev>
License-Expression: MIT
Requires-Dist: prompt-toolkit>=3.0.19,<4.0.0
Requires-Python: >=3.9, <4.0
Project-URL: documentation, https://github.com/nonebot/noneprompt
Project-URL: homepage, https://github.com/nonebot/noneprompt
Project-URL: repository, https://github.com/nonebot/noneprompt
